timing_utils/__init__.py
timing_utils/decorators.py
timing_utils-0.1.3.dist-info/METADATA
timing_utils-0.1.3.dist-info/WHEEL
timing_utils-0.1.3.dist-info/RECORD
