Metadata-Version: 2.4
Name: timing-utils
Version: 0.1.3
Summary: Simple utilities to time synchronous and asynchronous Python functions.
Project-URL: Homepage, https://github.com/tyrbok/timing-utils
Project-URL: Repository, https://github.com/tyrbok/timing-utils
Author-email: Jesus Serrano <jesus@onepointzero.org>
License: MIT
Requires-Python: >=3.8
Requires-Dist: loguru>=0.7.0
Provides-Extra: dev
Requires-Dist: build; extra == 'dev'
Requires-Dist: pytest-asyncio; extra == 'dev'
Requires-Dist: pytest>=8.1; extra == 'dev'
Requires-Dist: ruff; extra == 'dev'
Requires-Dist: tox>=4.0; extra == 'dev'
Requires-Dist: twine; extra == 'dev'
